jobmon_pkg/__init__.py
jobmon_pkg/cli.py
jobmon_pkg/scripts/jobmon.sh
jobmon_slurm-2.0.0.dist-info/METADATA
jobmon_slurm-2.0.0.dist-info/WHEEL
jobmon_slurm-2.0.0.dist-info/entry_points.txt
jobmon_slurm-2.0.0.dist-info/top_level.txt
jobmon_slurm-2.0.0.dist-info/RECORD
