Metadata-Version: 2.2
Name: jobmon-slurm
Version: 2.0.0
Summary: Enhanced Universal SLURM Job Monitor with smart pattern matching
Home-page: https://github.com/omonidat/jobmon-slurm
Author: Shafeeq Ibraheem
Author-email: omonidat@example.com
Project-URL: Bug Reports, https://github.com/omonidat/jobmon-slurm/issues
Project-URL: Source, https://github.com/omonidat/jobmon-slurm/
Project-URL: Documentation, https://github.com/omonidat/jobmon-slurm/blob/main/README.md
Keywords: slurm hpc job monitoring cluster computing batch scheduler
Classifier: Development Status :: 4 - Beta
Classifier: Intended Audience :: Science/Research
Classifier: Topic :: System :: Monitoring
Classifier: Topic :: System :: Systems Administration
Classifier: License :: OSI Approved :: MIT License
Classifier: Programming Language :: Python :: 3
Classifier: Programming Language :: Python :: 3.6
Classifier: Programming Language :: Python :: 3.7
Classifier: Programming Language :: Python :: 3.8
Classifier: Programming Language :: Python :: 3.9
Classifier: Programming Language :: Python :: 3.10
Classifier: Programming Language :: Python :: 3.11
Classifier: Operating System :: POSIX :: Linux
Classifier: Environment :: Console
Requires-Python: >=3.6
Provides-Extra: dev
Requires-Dist: wheel; extra == "dev"
Requires-Dist: twine; extra == "dev"
Requires-Dist: pytest; extra == "dev"
Requires-Dist: black; extra == "dev"
Dynamic: author
Dynamic: author-email
Dynamic: classifier
Dynamic: description
Dynamic: description-content-type
Dynamic: home-page
Dynamic: keywords
Dynamic: project-url
Dynamic: provides-extra
Dynamic: requires-python
Dynamic: summary
